hls_editor/__init__.py
hls_editor/__main__.py
hls_editor/exception.py
hls_editor/hls_editor.py
hls_editor/hls_helper.py
hls_edit_file-0.0.1.dist-info/METADATA
hls_edit_file-0.0.1.dist-info/WHEEL
hls_edit_file-0.0.1.dist-info/top_level.txt
hls_edit_file-0.0.1.dist-info/RECORD
