Metadata-Version: 2.1
Name: hls-edit-file
Version: 0.0.1
Summary: Package support cut, merge, insert hls video into hls video (m3u8)
Home-page: https://github.com/cptrodgers/hls-edit-file
Author: Rodgers Nguyen
Author-email: cptrodgers@gmail.com
License: UNKNOWN
Platform: UNKNOWN
Classifier: Programming Language :: Python :: 2
Classifier: License :: OSI Approved :: MIT License
Classifier: Operating System :: OS Independent
